sisl_gui/__init__.py
sisl_gui/launch.py
sisl_gui/sgui.py
sisl_gui/build/SIESTAlogo.png
sisl_gui/build/apple-touch-icon.png
sisl_gui/build/asset-manifest.json
sisl_gui/build/electron.js
sisl_gui/build/favicon-32x32.png
sisl_gui/build/favicon.ico
sisl_gui/build/icon.icns
sisl_gui/build/index.html
sisl_gui/build/manifest.json
sisl_gui/build/mstile-150x150.png
sisl_gui/build/pyodide-webworker.js
sisl_gui/build/robots.txt
sisl_gui/build/safari-pinned-tab.svg
sisl_gui/build/sisl-0.14.4.dev295+g00b8afa29d-cp312-cp312-emscripten_3_1_52_wasm32.whl
sisl_gui/build/static/css/main.b43e89bd.css
sisl_gui/build/static/css/main.b43e89bd.css.map
sisl_gui/build/static/js/main.ae0b701a.js
sisl_gui/build/static/js/main.ae0b701a.js.LICENSE.txt
sisl_gui/build/static/js/main.ae0b701a.js.map
sisl_gui/server/__init__.py
sisl_gui/server/app.py
sisl_gui/server/json.py
sisl_gui/server/pyodide.py
sisl_gui/server/session.py
sisl_gui/server/sync.py
sisl_gui/server/flask_socketio/__init__.py
sisl_gui/server/flask_socketio/app.py
sisl_gui/server/flask_socketio/emiters.py
sisl_gui/server/flask_socketio/sync.py
sisl_gui/server/flask_socketio/user_management.py
sisl_gui-0.4.1.dist-info/METADATA
sisl_gui-0.4.1.dist-info/WHEEL
sisl_gui-0.4.1.dist-info/entry_points.txt
sisl_gui-0.4.1.dist-info/top_level.txt
sisl_gui-0.4.1.dist-info/RECORD
