Metadata-Version: 2.1
Name: sisl-gui
Version: 0.4.1
Summary: Graphical interface for the sisl visualization module
Home-page: http://github.com/pfebrer/sisl-gui
Author: Pol Febrer
Author-email: pfebrer96@gmail.com
License: MIT
Platform: UNKNOWN
Requires-Dist: sisl
Requires-Dist: plotly
Requires-Dist: xarray
Requires-Dist: pandas
Requires-Dist: dill >=0.3.2
Requires-Dist: pathos
Requires-Dist: scikit-image
Requires-Dist: simplejson
Requires-Dist: flask
Requires-Dist: flask-socketio >=5.0
Requires-Dist: flask-login
Requires-Dist: flask-session
Requires-Dist: simple-websocket
Requires-Dist: eventlet
